meeting_timer/__init__.py
meeting_timer/application.py
meeting_timer/display_window.py
meeting_timer/main.py
meeting_timer/main_window.py
meeting_timer/meetingtime.py
meeting_timer/settings.py
meeting_timer/settings_window.py
meeting_timer/support.py
meeting_timer/webcam_output.py
meeting_timer-0.3.0.dist-info/LICENSE
meeting_timer-0.3.0.dist-info/METADATA
meeting_timer-0.3.0.dist-info/WHEEL
meeting_timer-0.3.0.dist-info/entry_points.txt
meeting_timer-0.3.0.dist-info/top_level.txt
meeting_timer-0.3.0.dist-info/RECORD
