Metadata-Version: 2.1
Name: meeting-timer
Version: 0.3.0
Summary: A simple application to allow you to keep your meetings or webinars running on time.
Home-page: https://github.com/andrewjrobinson/meeting_timer
Author: Andrew Robinson
Author-email: andrewjrobinson+mt@gmail.com
License: MIT
Platform: UNKNOWN
Classifier: Programming Language :: Python :: 3
Classifier: License :: OSI Approved :: MIT License
Classifier: Operating System :: OS Independent
Requires-Python: >=3.6
